virtManager/__init__.py
virtManager/about.py
virtManager/addhardware.py
virtManager/addstorage.py
virtManager/asyncjob.py
virtManager/baseclass.py
virtManager/choosecd.py
virtManager/clone.py
virtManager/config.py
virtManager/connect.py
virtManager/connectauth.py
virtManager/connection.py
virtManager/console.py
virtManager/create.py
virtManager/createinterface.py
virtManager/createnet.py
virtManager/createpool.py
virtManager/createvol.py
virtManager/delete.py
virtManager/details.py
virtManager/domain.py
virtManager/engine.py
virtManager/error.py
virtManager/fsdetails.py
virtManager/gfxdetails.py
virtManager/graphwidgets.py
virtManager/host.py
virtManager/inspection.py
virtManager/interface.py
virtManager/keyring.py
virtManager/libvirtobject.py
virtManager/manager.py
virtManager/mediacombo.py
virtManager/migrate.py
virtManager/module_trace.py
virtManager/netlist.py
virtManager/network.py
virtManager/nodedev.py
virtManager/packageutils.py
virtManager/preferences.py
virtManager/serialcon.py
virtManager/snapshots.py
virtManager/sshtunnels.py
virtManager/storagebrowse.py
virtManager/storagelist.py
virtManager/storagepool.py
virtManager/systray.py
virtManager/uiutil.py
virtManager/viewers.py
virtManager/vmmenu.py
virt_manager_pure_cli_yen3-1.5.0.3.data/scripts/virt-clone
virt_manager_pure_cli_yen3-1.5.0.3.data/scripts/virt-convert
virt_manager_pure_cli_yen3-1.5.0.3.data/scripts/virt-install
virt_manager_pure_cli_yen3-1.5.0.3.data/scripts/virt-xml
virt_manager_pure_cli_yen3-1.5.0.3.dist-info/DESCRIPTION.rst
virt_manager_pure_cli_yen3-1.5.0.3.dist-info/METADATA
virt_manager_pure_cli_yen3-1.5.0.3.dist-info/RECORD
virt_manager_pure_cli_yen3-1.5.0.3.dist-info/WHEEL
virt_manager_pure_cli_yen3-1.5.0.3.dist-info/metadata.json
virt_manager_pure_cli_yen3-1.5.0.3.dist-info/top_level.txt
virtcli/__init__.py
virtcli/cliconfig.py
virtconv/__init__.py
virtconv/formats.py
virtconv/ovf.py
virtconv/vmx.py
virtinst/__init__.py
virtinst/capabilities.py
virtinst/cli.py
virtinst/clock.py
virtinst/cloner.py
virtinst/connection.py
virtinst/cpu.py
virtinst/cputune.py
virtinst/device.py
virtinst/deviceaudio.py
virtinst/devicechar.py
virtinst/devicecontroller.py
virtinst/devicedisk.py
virtinst/devicefilesystem.py
virtinst/devicegraphics.py
