Metadata-Version: 2.0
Name: virt-manager-pure-cli-yen3
Version: 1.5.0.3
Summary: virt-manager purl cli
Home-page: UNKNOWN
Author: Red hat
Author-email: UNKNOWN
License: MIT
Platform: UNKNOWN
Classifier: Programming Language :: Python :: 2.7
Requires-Dist: ipaddr
Requires-Dist: requests
Requires-Dist: libvirt-python (==4.0.0)
